seano_cli/__init__.py
seano_cli/cli.py
seano_cli/constants.py
seano_cli/utils.py
seano_cli/cmd/__init__.py
seano_cli/cmd/edit_note.py
seano_cli/cmd/format_query_output.py
seano_cli/cmd/hash_repo.py
seano_cli/cmd/import_from_submodules.py
seano_cli/cmd/init_note.py
seano_cli/cmd/init_repo.py
seano_cli/cmd/list_notes.py
seano_cli/cmd/mark_as_ghost.py
seano_cli/cmd/query_repo.py
seano_cli/db/__init__.py
seano_cli/db/auto_detect.py
seano_cli/db/common.py
seano_cli/db/dumb.py
seano_cli/db/generic.py
seano_cli/db/git.py
seano_cli/db/release_sorting.py
seano_cli/db/schema_upgrade.py
seano_cli-2.0.2.dist-info/licenses/LICENSE
seano_cli-2.0.2.dist-info/METADATA
seano_cli-2.0.2.dist-info/WHEEL
seano_cli-2.0.2.dist-info/entry_points.txt
seano_cli-2.0.2.dist-info/top_level.txt
seano_cli-2.0.2.dist-info/RECORD
